{
  "indexes": [
    {
      "collectionGroup": "sacrament-submissions",
      "queryScope": "COLLECTION",
      "fields": [
        {
          "fieldPath": "type",
          "order": "ASCENDING"
        },
        {
          "fieldPath": "submittedAt",
          "order": "DESCENDING"
        }
      ]
    },
    {
      "collectionGroup": "sacrament-submissions",
      "queryScope": "COLLECTION",
      "fields": [
        {
          "fieldPath": "status",
          "order": "ASCENDING"
        },
        {
          "fieldPath": "submittedAt",
          "order": "DESCENDING"
        }
      ]
    },
    {
      "collectionGroup": "sacrament-submissions",
      "queryScope": "COLLECTION",
      "fields": [
        {
          "fieldPath": "type",
          "order": "ASCENDING"
        },
        {
          "fieldPath": "status",
          "order": "ASCENDING"
        },
        {
          "fieldPath": "submittedAt",
          "order": "DESCENDING"
        }
      ]
    },
    {
      "collectionGroup": "join-us-submissions",
      "queryScope": "COLLECTION",
      "fields": [
        {
          "fieldPath": "type",
          "order": "ASCENDING"
        },
        {
          "fieldPath": "submittedAt",
          "order": "DESCENDING"
        }
      ]
    },
    {
      "collectionGroup": "join-us-submissions",
      "queryScope": "COLLECTION",
      "fields": [
        {
          "fieldPath": "status",
          "order": "ASCENDING"
        },
        {
          "fieldPath": "submittedAt",
          "order": "DESCENDING"
        }
      ]
    },
    {
      "collectionGroup": "join-us-submissions",
      "queryScope": "COLLECTION",
      "fields": [
        {
          "fieldPath": "type",
          "order": "ASCENDING"
        },
        {
          "fieldPath": "status",
          "order": "ASCENDING"
        },
        {
          "fieldPath": "submittedAt",
          "order": "DESCENDING"
        }
      ]
    },
    {
      "collectionGroup": "mass-intentions-submissions",
      "queryScope": "COLLECTION",
      "fields": [
        {
          "fieldPath": "status",
          "order": "ASCENDING"
        },
        {
          "fieldPath": "submittedAt",
          "order": "DESCENDING"
        }
      ]
    },
    {
      "collectionGroup": "donations-submissions",
      "queryScope": "COLLECTION",
      "fields": [
        {
          "fieldPath": "status",
          "order": "ASCENDING"
        },
        {
          "fieldPath": "submittedAt",
          "order": "DESCENDING"
        }
      ]
    },
    {
      "collectionGroup": "contact-us-submissions",
      "queryScope": "COLLECTION",
      "fields": [
        {
          "fieldPath": "status",
          "order": "ASCENDING"
        },
        {
          "fieldPath": "submittedAt",
          "order": "DESCENDING"
        }
      ]
    }
  ],
  "fieldOverrides": []
}
